<?xml version="1.0" encoding="UTF-8"?>
<objects serializationModel="Studio.02.03.00">
	<object class="AudioFile" id="{3db004e3-b6c8-466a-bcd6-205ed2b13c5f}">
		<property name="assetPath">
			<value>Music/Lvl2Music.mp3</value>
		</property>
		<property name="isStreaming">
			<value>true</value>
		</property>
		<property name="frequencyInKHz">
			<value>44.0999985</value>
		</property>
		<property name="channelCount">
			<value>2</value>
		</property>
		<property name="length">
			<value>100.51918367346939</value>
		</property>
		<relationship name="masterAssetFolder">
			<destination>{2c6e6fb9-cb0a-43e9-8acd-36c935c71499}</destination>
		</relationship>
	</object>
</objects>
